<annotation>
	<folder>32ad92c5356b4b27</folder>
	<filename>20220423225754.jpg</filename>
	<path>E:\Work\Develop\License\ev_charge_train_pic\32ad92c5356b4b27\20220423225754.jpg</path>
	<source>
		<database>Unknown</database>
	</source>
	<size>
		<width>1920</width>
		<height>1080</height>
		<depth>3</depth>
	</size>
	<segmented>0</segmented>
	<object>
		<name>space</name>
		<pose>Unspecified</pose>
		<truncated>0</truncated>
		<difficult>0</difficult>
		<bndbox>
			<xmin>574</xmin>
			<ymin>270</ymin>
			<xmax>1335</xmax>
			<ymax>757</ymax>
		</bndbox>
	</object>
	<object>
		<name>car</name>
		<pose>Unspecified</pose>
		<truncated>0</truncated>
		<difficult>0</difficult>
		<bndbox>
			<xmin>1133</xmin>
			<ymin>124</ymin>
			<xmax>1772</xmax>
			<ymax>672</ymax>
		</bndbox>
	</object>
	<object>
		<name>plate</name>
		<pose>Unspecified</pose>
		<truncated>0</truncated>
		<difficult>0</difficult>
		<bndbox>
			<xmin>1515</xmin>
			<ymin>566</ymin>
			<xmax>1662</xmax>
			<ymax>622</ymax>
		</bndbox>
	</object>
</annotation>
