<annotation>
	<folder>5941a564384f3d8a</folder>
	<filename>20220423145007.jpg</filename>
	<path>E:\Work\Develop\License\ev_charge_train_pic\5941a564384f3d8a\20220423145007.jpg</path>
	<source>
		<database>Unknown</database>
	</source>
	<size>
		<width>1920</width>
		<height>1080</height>
		<depth>3</depth>
	</size>
	<segmented>0</segmented>
	<object>
		<name>car</name>
		<pose>Unspecified</pose>
		<truncated>0</truncated>
		<difficult>0</difficult>
		<bndbox>
			<xmin>111</xmin>
			<ymin>245</ymin>
			<xmax>669</xmax>
			<ymax>795</ymax>
		</bndbox>
	</object>
	<object>
		<name>car</name>
		<pose>Unspecified</pose>
		<truncated>0</truncated>
		<difficult>0</difficult>
		<bndbox>
			<xmin>712</xmin>
			<ymin>231</ymin>
			<xmax>1278</xmax>
			<ymax>844</ymax>
		</bndbox>
	</object>
	<object>
		<name>car</name>
		<pose>Unspecified</pose>
		<truncated>0</truncated>
		<difficult>0</difficult>
		<bndbox>
			<xmin>1197</xmin>
			<ymin>227</ymin>
			<xmax>1869</xmax>
			<ymax>791</ymax>
		</bndbox>
	</object>
	<object>
		<name>plate</name>
		<pose>Unspecified</pose>
		<truncated>0</truncated>
		<difficult>0</difficult>
		<bndbox>
			<xmin>195</xmin>
			<ymin>685</ymin>
			<xmax>341</xmax>
			<ymax>741</ymax>
		</bndbox>
	</object>
	<object>
		<name>plate</name>
		<pose>Unspecified</pose>
		<truncated>0</truncated>
		<difficult>0</difficult>
		<bndbox>
			<xmin>1661</xmin>
			<ymin>653</ymin>
			<xmax>1791</xmax>
			<ymax>713</ymax>
		</bndbox>
	</object>
</annotation>
